{
  "experiment_id": "VulBERTa_mlp_007_parallel",
  "timestamp": "2025-12-15T01:24:16.509398",
  "mode": "parallel",
  "foreground": {
    "repository": "VulBERTa",
    "model": "mlp",
    "hyperparameters": {
      "weight_decay": 1.620273741011439e-05
    },
    "duration_seconds": 3779.654055595398,
    "energy_metrics": {
      "cpu_energy_pkg_joules": 135642.87,
      "cpu_energy_ram_joules": 9217.14,
      "cpu_energy_total_joules": 144860.01,
      "gpu_power_avg_watts": 237.91010589193593,
      "gpu_power_max_watts": 319.46,
      "gpu_power_min_watts": 89.0,
      "gpu_energy_total_joules": 876222.92,
      "gpu_temp_avg_celsius": 78.95574260114037,
      "gpu_temp_max_celsius": 84.0,
      "gpu_util_avg_percent": 91.72386641325006,
      "gpu_util_max_percent": 100.0
    },
    "performance_metrics": {
      "eval_loss": 0.683940052986145,
      "final_training_loss": 0.7466,
      "eval_samples_per_second": 49.141
    },
    "training_success": true,
    "retries": 0,
    "error_message": "Training completed successfully"
  },
  "background": {
    "repository": "examples",
    "model": "mnist",
    "hyperparameters": {
      "epochs": 10,
      "learning_rate": 0.01,
      "batch_size": 32,
      "seed": 1
    },
    "log_directory": "/home/green/energy_dl/nightly/results/run_20251214_160925/VulBERTa_mlp_007_parallel/background_logs",
    "note": "Background training served as GPU load only (not monitored)"
  }
}