{
  "experiment_id": "examples_mnist_001",
  "timestamp": "2025-12-05T21:20:19.281059",
  "repository": "examples",
  "model": "mnist",
  "hyperparameters": {
    "epochs": 13,
    "learning_rate": 0.012196642228041461,
    "batch_size": 62,
    "seed": 7527
  },
  "duration_seconds": 172.65144658088684,
  "energy_metrics": {
    "cpu_energy_pkg_joules": 5331.68,
    "cpu_energy_ram_joules": 409.83,
    "cpu_energy_total_joules": 5741.51,
    "gpu_power_avg_watts": 90.17506024096384,
    "gpu_power_max_watts": 93.16,
    "gpu_power_min_watts": 69.42,
    "gpu_energy_total_joules": 14969.059999999998,
    "gpu_temp_avg_celsius": 52.596385542168676,
    "gpu_temp_max_celsius": 57.0,
    "gpu_util_avg_percent": 9.301204819277109,
    "gpu_util_max_percent": 11.0
  },
  "performance_metrics": {
    "test_accuracy": 96.0,
    "test_loss": 0.132
  },
  "training_success": true,
  "retries": 0,
  "error_message": "Training completed successfully"
}