{
  "experiment_id": "examples_mnist_ff_088",
  "timestamp": "2025-11-28T17:30:02.435002",
  "repository": "examples",
  "model": "mnist_ff",
  "hyperparameters": {
    "learning_rate": 0.014657713959024628
  },
  "duration_seconds": 17.722663164138794,
  "energy_metrics": {
    "cpu_energy_pkg_joules": 494.1,
    "cpu_energy_ram_joules": 40.39,
    "cpu_energy_total_joules": 534.49,
    "gpu_power_avg_watts": 177.85333333333332,
    "gpu_power_max_watts": 318.66,
    "gpu_power_min_watts": 73.18,
    "gpu_energy_total_joules": 2667.7999999999997,
    "gpu_temp_avg_celsius": 63.93333333333333,
    "gpu_temp_max_celsius": 72.0,
    "gpu_util_avg_percent": 40.4,
    "gpu_util_max_percent": 100.0
  },
  "performance_metrics": {},
  "training_success": true,
  "retries": 0,
  "error_message": "Training completed successfully"
}