{
  "experiment_id": "VulBERTa_cnn_101_parallel",
  "timestamp": "2025-12-10T18:20:46.075848",
  "mode": "parallel",
  "foreground": {
    "repository": "VulBERTa",
    "model": "cnn",
    "hyperparameters": {
      "weight_decay": 0.00034445063256881883
    },
    "duration_seconds": 3.3627848625183105,
    "energy_metrics": {
      "cpu_energy_pkg_joules": 85.31,
      "cpu_energy_ram_joules": 5.81,
      "cpu_energy_total_joules": 91.12,
      "gpu_power_avg_watts": 260.51,
      "gpu_power_max_watts": 264.88,
      "gpu_power_min_watts": 257.53,
      "gpu_energy_total_joules": 781.53,
      "gpu_temp_avg_celsius": 77.0,
      "gpu_temp_max_celsius": 77.0,
      "gpu_util_avg_percent": 72.33333333333333,
      "gpu_util_max_percent": 73.0
    },
    "performance_metrics": {},
    "training_success": true,
    "retries": 0,
    "error_message": "Training completed successfully"
  },
  "background": {
    "repository": "Person_reID_baseline_pytorch",
    "model": "densenet121",
    "hyperparameters": {},
    "log_directory": "/home/green/energy_dl/nightly/results/run_20251208_174625/VulBERTa_cnn_101_parallel/background_logs",
    "note": "Background training served as GPU load only (not monitored)"
  }
}