{
  "experiment_id": "MRT-OAST_default_002",
  "timestamp": "2025-11-26T23:32:14.385068",
  "repository": "MRT-OAST",
  "model": "default",
  "hyperparameters": {
    "epochs": 12
  },
  "duration_seconds": 1561.193340063095,
  "energy_metrics": {
    "cpu_energy_pkg_joules": 46239.05,
    "cpu_energy_ram_joules": 3513.29,
    "cpu_energy_total_joules": 49752.34,
    "gpu_power_avg_watts": 238.4233135313529,
    "gpu_power_max_watts": 317.91,
    "gpu_power_min_watts": 76.43,
    "gpu_energy_total_joules": 361211.31999999966,
    "gpu_temp_avg_celsius": 79.53201320132013,
    "gpu_temp_max_celsius": 84.0,
    "gpu_util_avg_percent": 92.92541254125412,
    "gpu_util_max_percent": 100.0
  },
  "performance_metrics": {
    "accuracy": 4745.0,
    "precision": 0.986171,
    "recall": 0.855606
  },
  "training_success": true,
  "retries": 0,
  "error_message": "Training completed successfully"
}