{
  "experiment_id": "bug-localization-by-dnn-and-rvsm_default_110_parallel",
  "timestamp": "2026-01-02T10:42:47.817067",
  "mode": "parallel",
  "foreground": {
    "repository": "bug-localization-by-dnn-and-rvsm",
    "model": "default",
    "hyperparameters": {
      "alpha": 8.627707412299589e-06,
      "kfold": 9,
      "max_iter": 3305,
      "seed": 8065
    },
    "duration_seconds": 873.1160900592804,
    "energy_metrics": {
      "cpu_energy_pkg_joules": 57693.29,
      "cpu_energy_ram_joules": 2209.3,
      "cpu_energy_total_joules": 59902.59,
      "gpu_power_avg_watts": 87.56461103253183,
      "gpu_power_max_watts": 94.64,
      "gpu_power_min_watts": 61.11,
      "gpu_energy_total_joules": 61908.18,
      "gpu_temp_avg_celsius": 62.23762376237624,
      "gpu_temp_max_celsius": 63.0,
      "gpu_util_avg_percent": 3.7496463932107496,
      "gpu_util_max_percent": 14.0
    },
    "performance_metrics": {
      "top1_accuracy": 0.373,
      "top5_accuracy": 0.625,
      "top10_accuracy": 0.738,
      "top20_accuracy": 0.826
    },
    "training_success": true,
    "retries": 0,
    "error_message": "Training completed successfully"
  },
  "background": {
    "repository": "examples",
    "model": "mnist",
    "hyperparameters": {},
    "log_directory": "/home/green/energy_dl/nightly/results/run_20251230_204245/bug-localization-by-dnn-and-rvsm_default_110_parallel/background_logs",
    "note": "Background training served as GPU load only (not monitored)"
  }
}